<annotation>
	<folder>images</folder>
	<filename>002934e5712ba154.jpg</filename>
	<path>C:\tensorflow1\models\research\object_detection\images\002934e5712ba154.jpg</path>
	<source>
		<database>Unknown</database>
	</source>
	<size>
		<width>200</width>
		<height>133</height>
		<depth>3</depth>
	</size>
	<segmented>0</segmented>
	<object>
		<name>car</name>
		<pose>Unspecified</pose>
		<truncated>0</truncated>
		<difficult>0</difficult>
		<bndbox>
			<xmin>10</xmin>
			<ymin>39</ymin>
			<xmax>186</xmax>
			<ymax>116</ymax>
		</bndbox>
	</object>
	<object>
		<name>car</name>
		<pose>Unspecified</pose>
		<truncated>0</truncated>
		<difficult>0</difficult>
		<bndbox>
			<xmin>24</xmin>
			<ymin>38</ymin>
			<xmax>49</xmax>
			<ymax>65</ymax>
		</bndbox>
	</object>
</annotation>
